graph_flat_norm/2d_lookup_table.npz
graph_flat_norm/__init__.py
graph_flat_norm/flat_norm.py
graph_flat_norm/graph_solver.py
graph_flat_norm/kdtree.py
graph_flat_norm/sys_reducer.py
graph_flat_norm/voronoi.py
graph_flat_norm/weights_system.py
graph_flat_norm-0.0.7.dist-info/METADATA
graph_flat_norm-0.0.7.dist-info/WHEEL
graph_flat_norm-0.0.7.dist-info/licenses/LICENSE
graph_flat_norm-0.0.7.dist-info/RECORD
