Metadata-Version: 2.3
Name: graph_flat_norm
Version: 0.0.7
Dynamic: Requires-Dist
Summary: package for computing the flat norm on euclidean graphs
Project-URL: Homepage, https://github.com/bcecil2/flat_norm_on_graphs
Project-URL: Issues, https://github.com/bcecil2/flat_norm_on_graphs/issues
Author: Blake Cecil
Author-email: Curtis Michels <iscicodes@proton.me>
License: The MIT License (MIT)
License-File: LICENSE
Classifier: License :: OSI Approved :: MIT License
Classifier: Operating System :: OS Independent
Classifier: Programming Language :: Python :: 3
Requires-Python: >=3.9
